pypy_geoff/__init__.py
pypy_geoff-0.1.3.dist-info/LICENSE
pypy_geoff-0.1.3.dist-info/WHEEL
pypy_geoff-0.1.3.dist-info/METADATA
pypy_geoff-0.1.3.dist-info/RECORD
