Metadata-Version: 2.1
Name: pypy-geoff
Version: 0.1.3
Summary: 
Author: Geoff Dutton
Author-email: g.dutton@gmail.com
Requires-Python: >=3.8,<4.0
Classifier: Programming Language :: Python :: 3
Classifier: Programming Language :: Python :: 3.10
Classifier: Programming Language :: Python :: 3.8
Classifier: Programming Language :: Python :: 3.9
